pm/process_video/__about__.py
pm/process_video/__init__.py
pm/process_video/__main__.py
pm_process_video-0.0.2.dist-info/METADATA
pm_process_video-0.0.2.dist-info/WHEEL
pm_process_video-0.0.2.dist-info/entry_points.txt
pm_process_video-0.0.2.dist-info/licenses/LICENSE.txt
pm_process_video-0.0.2.dist-info/RECORD
